<?xml version="1.0" encoding="utf-8"?>
<LanguageData>

	<Turret_M2HBT.label>双联装M2HB重机枪塔</Turret_M2HBT.label>
	<Turret_M2HBT.description>一个美国的重型机枪，双联安装在手动炮塔上，适合对付步兵，轻型装甲车和简单的防御工事。可以接受直接控制，但请小心友方的火力。</Turret_M2HBT.description>
	<Turret_M2HBT_Blueprint.label>双联装M2HB重机枪塔 (蓝图)</Turret_M2HBT_Blueprint.label>
	<Turret_M2HBT_Blueprint_Install.label>双联装M2HB重机枪塔 (安装中)</Turret_M2HBT_Blueprint_Install.label>
	<Turret_M2HBT_Frame.label>双联装M2HB重机枪塔 (建造中)</Turret_M2HBT_Frame.label>
	<Turret_M2HBT_Frame.description>一个美国的重型机枪，双联安装在手动炮塔上，适合对付步兵，轻型装甲车和简单的防御工事。可以接受直接控制，但请小心友方的火力。</Turret_M2HBT_Frame.description>

	<Bullet_M2HBT.label>.50 BMG 子弹</Bullet_M2HBT.label>

	<Gun_M2HBT.label>双联装M2HB重机枪</Gun_M2HBT.label>
	<Gun_M2HBT.description>一个美国的重型机枪，用于双联安装在炮塔上。</Gun_M2HBT.description>

	<Turret_M2HBT.comps.CompRefuelable.fuelGizmoLabel>枪管耐久值</Turret_M2HBT.comps.CompRefuelable.fuelGizmoLabel>
	<Turret_M2HBT.comps.CompRefuelable.fuelLabel>重新装填后继续开火</Turret_M2HBT.comps.CompRefuelable.fuelLabel>
	<Turret_M2HBT.comps.CompRefuelable.outOfFuelMessage>无法开火：需要装填</Turret_M2HBT.comps.CompRefuelable.outOfFuelMessage>

</LanguageData>